setup.py
DingyiTools/__init__.py
DingyiTools/file_parser.py
DingyiTools.egg-info/PKG-INFO
DingyiTools.egg-info/SOURCES.txt
DingyiTools.egg-info/dependency_links.txt
DingyiTools.egg-info/top_level.txt